airflow/providers/apache/spark/__init__.py
airflow/providers/apache/spark/get_provider_info.py
airflow/providers/apache/spark/version_compat.py
airflow/providers/apache/spark/decorators/__init__.py
airflow/providers/apache/spark/decorators/pyspark.py
airflow/providers/apache/spark/hooks/__init__.py
airflow/providers/apache/spark/hooks/spark_connect.py
airflow/providers/apache/spark/hooks/spark_jdbc.py
airflow/providers/apache/spark/hooks/spark_jdbc_script.py
airflow/providers/apache/spark/hooks/spark_sql.py
airflow/providers/apache/spark/hooks/spark_submit.py
airflow/providers/apache/spark/operators/__init__.py
airflow/providers/apache/spark/operators/spark_jdbc.py
airflow/providers/apache/spark/operators/spark_pyspark.py
airflow/providers/apache/spark/operators/spark_sql.py
airflow/providers/apache/spark/operators/spark_submit.py
apache_airflow_providers_apache_spark-5.5.0.dist-info/entry_points.txt
apache_airflow_providers_apache_spark-5.5.0.dist-info/licenses/LICENSE
apache_airflow_providers_apache_spark-5.5.0.dist-info/licenses/NOTICE
apache_airflow_providers_apache_spark-5.5.0.dist-info/WHEEL
apache_airflow_providers_apache_spark-5.5.0.dist-info/METADATA
apache_airflow_providers_apache_spark-5.5.0.dist-info/RECORD
